eigenstrapping/__init__.py
eigenstrapping/base.py
eigenstrapping/dataio.py
eigenstrapping/fit.py
eigenstrapping/geometry.py
eigenstrapping/parutils.py
eigenstrapping/plotting.py
eigenstrapping/rotations.py
eigenstrapping/spatial.py
eigenstrapping/stats.py
eigenstrapping/utils.py
eigenstrapping/datasets/__init__.py
eigenstrapping/datasets/base.py
eigenstrapping/datasets/utils.py
eigenstrapping-0.0.1.10.dist-info/LICENSE
eigenstrapping-0.0.1.10.dist-info/METADATA
eigenstrapping-0.0.1.10.dist-info/WHEEL
eigenstrapping-0.0.1.10.dist-info/top_level.txt
eigenstrapping-0.0.1.10.dist-info/RECORD
