Metadata-Version: 2.1
Name: eigenstrapping
Version: 0.0.1.10
Summary: For generating surrogate brain maps with spatial autocorrelation using geometric eigenmodes.
Home-page: https://github.com/SNG-newy/eigenstrapping
Author: Nikitas C. Koussis, Systems Neuroscience Group Newcastle
Author-email: "Nikitas C. Koussis" <nikitas.koussis@gmail.com>
License: GNU GENERAL PUBLIC LICENSE
Project-URL: Source, https://github.com/SNG-newy/eigenstrapping
Project-URL: Documentation, https://github.com/SNG-newy/eigenstrapping
License-File: LICENSE
Requires-Dist: brainsmash ==0.11.0
Requires-Dist: brainspace ==0.1.10
Requires-Dist: joblib
Requires-Dist: parspin
Requires-Dist: lapy ==1.0.1
Requires-Dist: matplotlib
Requires-Dist: neuromaps
Requires-Dist: nibabel
Requires-Dist: nilearn
Requires-Dist: numpy
Requires-Dist: pandas
Requires-Dist: scipy >=0.11
Requires-Dist: seaborn
Requires-Dist: tqdm
